CVLDoc/__init__.py
CVLDoc/natspec_to_json.py
CVLDoc-1.0.1.data/data/src/CVLDoc/examples/definition_test.spec
CVLDoc-1.0.1.data/data/src/CVLDoc/examples/full_contract.spec
CVLDoc-1.0.1.data/data/src/CVLDoc/examples/function_test.spec
CVLDoc-1.0.1.data/data/src/CVLDoc/examples/import_test.spec
CVLDoc-1.0.1.data/data/src/CVLDoc/examples/invariant_test.spec
CVLDoc-1.0.1.data/data/src/CVLDoc/examples/methods_test.spec
CVLDoc-1.0.1.data/data/src/CVLDoc/examples/rules_test.spec
CVLDoc-1.0.1.data/data/src/CVLDoc/examples/use_test.spec
CVLDoc-1.0.1.data/data/src/CVLDoc/examples/using_test.spec
CVLDoc-1.0.1.dist-info/LICENSE.txt
CVLDoc-1.0.1.dist-info/METADATA
CVLDoc-1.0.1.dist-info/WHEEL
CVLDoc-1.0.1.dist-info/entry_points.txt
CVLDoc-1.0.1.dist-info/top_level.txt
CVLDoc-1.0.1.dist-info/RECORD
