Metadata-Version: 2.1
Name: CVLDoc
Version: 1.0.1
Summary: Utility for reading CERTORA spec files, parse and export their NatSpec comments to JSON files.
Home-page: https://github.com/Certora/natspecTools
Author: Certora ltd
Author-email: support@certora.com
Keywords: Certora CVLDoc
Classifier: Programming Language :: Python :: 3
Classifier: License :: OSI Approved :: MIT License
Classifier: Operating System :: OS Independent
Classifier: Development Status :: 3 - Alpha
Requires-Python: >=3.7
License-File: LICENSE.txt
Requires-Dist: cvldoc-parser (==1.0.1)
Requires-Dist: inflection
